README.md
setup.cfg
setup.py
jamia_all_courses/__init__.py
jamia_all_courses.egg-info/PKG-INFO
jamia_all_courses.egg-info/SOURCES.txt
jamia_all_courses.egg-info/dependency_links.txt
jamia_all_courses.egg-info/top_level.txt