Metadata-Version: 2.1
Name: jamia-all-courses
Version: 1.2.0
Summary: A helpers for getting all courses available in Jamia Millia Islamia.
Home-page: https://github.com/Faisal-Manzer/jamia-all-courses
Author: Faisal Manzer
Author-email: faisal_manzer@yahoo.in
License: MIT
Download-URL: https://github.com/Faisal-Manzer/jamia-all-courses/archive/Python.tar.gz
Platform: UNKNOWN
Classifier: License :: OSI Approved :: MIT License
Classifier: Programming Language :: Python :: 3
Classifier: Programming Language :: Python :: 3.4
Classifier: Programming Language :: Python :: 3.5
Classifier: Programming Language :: Python :: 3.6
Classifier: Programming Language :: Python :: 3.7
